  <item>
    <title>PT: MUNDO TORO</title>
    <thumbnail>http://beststorage4you.com:80/logoscanais/Portugal.png</thumbnail>
    <link>http://unividia.com:80/746147216xtvs/w884E6734a/571518</link>
    <fanart></fanart>
    <info>Canais | Portugal</info>
  </item>
  <item>
    <title>PT-  UFC Figth Pass FHD</title>
    <thumbnail>http://beststorage4you.com:80/logoscanais/Portugal.png</thumbnail>
    <link>http://unividia.com:80/746147216xtvs/w884E6734a/112088</link>
    <fanart></fanart>
    <info>Canais | Portugal</info>
  </item>
  <item>
    <title>PT -NFL Network HD</title>
    <thumbnail>http://beststorage4you.com:80/logoscanais/Portugal.png</thumbnail>
    <link>http://unividia.com:80/746147216xtvs/w884E6734a/2475</link>
    <fanart></fanart>
    <info>Canais | Portugal</info>
  </item>
  <item>
    <title>PT- SportTV +  HD</title>
    <thumbnail>http://beststorage4you.com:80/logoscanais/Portugal.png</thumbnail>
    <link>http://unividia.com:80/746147216xtvs/w884E6734a/111993</link>
    <fanart></fanart>
    <info>Canais | Portugal</info>
  </item>
  <item>
    <title>PT- SportTV 1 HD</title>
    <thumbnail>http://beststorage4you.com:80/logoscanais/Portugal.png</thumbnail>
    <link>http://unividia.com:80/746147216xtvs/w884E6734a/111995</link>
    <fanart></fanart>
    <info>Canais | Portugal</info>
  </item>
  <item>
    <title>PT- SportTV 2 HD</title>
    <thumbnail>http://beststorage4you.com:80/logoscanais/Portugal.png</thumbnail>
    <link>http://unividia.com:80/746147216xtvs/w884E6734a/111998</link>
    <fanart></fanart>
    <info>Canais | Portugal</info>
  </item>
  <item>
    <title>PT- SportTV 3 HD</title>
    <thumbnail>http://beststorage4you.com:80/logoscanais/Portugal.png</thumbnail>
    <link>http://unividia.com:80/746147216xtvs/w884E6734a/112000</link>
    <fanart></fanart>
    <info>Canais | Portugal</info>
  </item>
  <item>
    <title>PT- SportTV 4 HD</title>
    <thumbnail>http://beststorage4you.com:80/logoscanais/Portugal.png</thumbnail>
    <link>http://unividia.com:80/746147216xtvs/w884E6734a/112002</link>
    <fanart></fanart>
    <info>Canais | Portugal</info>
  </item>
  <item>
    <title>PT- SportTV 5 HD</title>
    <thumbnail>http://beststorage4you.com:80/logoscanais/Portugal.png</thumbnail>
    <link>http://unividia.com:80/746147216xtvs/w884E6734a/112004</link>
    <fanart></fanart>
    <info>Canais | Portugal</info>
  </item>
  <item>
    <title>PT- SportTV 6 HD</title>
    <thumbnail>http://beststorage4you.com:80/logoscanais/Portugal.png</thumbnail>
    <link>http://unividia.com:80/746147216xtvs/w884E6734a/112006</link>
    <fanart></fanart>
    <info>Canais | Portugal</info>
  </item>
  <item>
    <title>PT- A Bola TV HD</title>
    <thumbnail>http://beststorage4you.com:80/logoscanais/Portugal.png</thumbnail>
    <link>http://unividia.com:80/746147216xtvs/w884E6734a/112014</link>
    <fanart></fanart>
    <info>Canais | Portugal</info>
  </item>
  <item>
    <title>PT- BLOOMBERG</title>
    <thumbnail>http://beststorage4you.com:80/logoscanais/Portugal.png</thumbnail>
    <link>http://unividia.com:80/746147216xtvs/w884E6734a/112030</link>
    <fanart></fanart>
    <info>Canais | Portugal</info>
  </item>
  <item>
    <title>PT- BTV HD</title>
    <thumbnail>http://beststorage4you.com:80/logoscanais/Portugal.png</thumbnail>
    <link>http://unividia.com:80/746147216xtvs/w884E6734a/112010</link>
    <fanart></fanart>
    <info>Canais | Portugal</info>
  </item>
  <item>
    <title>PT- CacaVision SD</title>
    <thumbnail>http://beststorage4you.com:80/logoscanais/Portugal.png</thumbnail>
    <link>http://unividia.com:80/746147216xtvs/w884E6734a/112078</link>
    <fanart></fanart>
    <info>Canais | Portugal</info>
  </item>
  <item>
    <title>PT- Canal 11 HD</title>
    <thumbnail>http://beststorage4you.com:80/logoscanais/Portugal.png</thumbnail>
    <link>http://unividia.com:80/746147216xtvs/w884E6734a/112016</link>
    <fanart></fanart>
    <info>Canais | Portugal</info>
  </item>
  <item>
    <title>PT- Canal180</title>
    <thumbnail>http://beststorage4you.com:80/logoscanais/Portugal.png</thumbnail>
    <link>http://unividia.com:80/746147216xtvs/w884E6734a/112102</link>
    <fanart></fanart>
    <info>Canais | Portugal</info>
  </item>
  <item>
    <title>PT- Canal Panda HD</title>
    <thumbnail>http://beststorage4you.com:80/logoscanais/Portugal.png</thumbnail>
    <link>http://unividia.com:80/746147216xtvs/w884E6734a/112026</link>
    <fanart></fanart>
    <info>Canais | Portugal</info>
  </item>
  <item>
    <title>Canal Q SD</title>
    <thumbnail>http://beststorage4you.com:80/logoscanais/Portugal.png</thumbnail>
    <link>http://unividia.com:80/746147216xtvs/w884E6734a/112052</link>
    <fanart></fanart>
    <info>Canais | Portugal</info>
  </item>
  <item>
    <title>Casa Cozinha HD</title>
    <thumbnail>http://beststorage4you.com:80/logoscanais/Portugal.png</thumbnail>
    <link>http://unividia.com:80/746147216xtvs/w884E6734a/112045</link>
    <fanart></fanart>
    <info>Canais | Portugal</info>
  </item>
  <item>
    <title>Caça & Pesca FHD</title>
    <thumbnail>http://beststorage4you.com:80/logoscanais/Portugal.png</thumbnail>
    <link>http://unividia.com:80/746147216xtvs/w884E6734a/112079</link>
    <fanart></fanart>
    <info>Canais | Portugal</info>
  </item>
  <item>
    <title>CBS Reality SD</title>
    <thumbnail>http://beststorage4you.com:80/logoscanais/Portugal.png</thumbnail>
    <link>http://unividia.com:80/746147216xtvs/w884E6734a/112043</link>
    <fanart></fanart>
    <info>Canais | Portugal</info>
  </item>
  <item>
    <title>Cine Mundo HD</title>
    <thumbnail>http://beststorage4you.com:80/logoscanais/Portugal.png</thumbnail>
    <link>http://unividia.com:80/746147216xtvs/w884E6734a/111971</link>
    <fanart></fanart>
    <info>Canais | Portugal</info>
  </item>
  <item>
    <title>Clubbing TV</title>
    <thumbnail>http://beststorage4you.com:80/logoscanais/Portugal.png</thumbnail>
    <link>http://unividia.com:80/746147216xtvs/w884E6734a/112101</link>
    <fanart></fanart>
    <info>Canais | Portugal</info>
  </item>
  <item>
    <title>CMTV HD</title>
    <thumbnail>http://beststorage4you.com:80/logoscanais/Portugal.png</thumbnail>
    <link>http://unividia.com:80/746147216xtvs/w884E6734a/111945</link>
    <fanart></fanart>
    <info>Canais | Portugal</info>
  </item>
  <item>
    <title>CNN HD</title>
    <thumbnail>http://beststorage4you.com:80/logoscanais/Portugal.png</thumbnail>
    <link>http://unividia.com:80/746147216xtvs/w884E6734a/111947</link>
    <fanart></fanart>
    <info>Canais | Portugal</info>
  </item>
  <item>
    <title>Crime Investigação SD</title>
    <thumbnail>http://beststorage4you.com:80/logoscanais/Portugal.png</thumbnail>
    <link>http://unividia.com:80/746147216xtvs/w884E6734a/112066</link>
    <fanart></fanart>
    <info>Canais | Portugal</info>
  </item>
  <item>
    <title>Discovery Channel HD</title>
    <thumbnail>http://beststorage4you.com:80/logoscanais/Portugal.png</thumbnail>
    <link>http://unividia.com:80/746147216xtvs/w884E6734a/112063</link>
    <fanart></fanart>
    <info>Canais | Portugal</info>
  </item>
  <item>
    <title>Discovery ID</title>
    <thumbnail>http://beststorage4you.com:80/logoscanais/Portugal.png</thumbnail>
    <link>http://unividia.com:80/746147216xtvs/w884E6734a/112067</link>
    <fanart></fanart>
    <info>Canais | Portugal</info>
  </item>
  <item>
    <title>Disney +</title>
    <thumbnail>http://beststorage4you.com:80/logoscanais/Portugal.png</thumbnail>
    <link>http://unividia.com:80/746147216xtvs/w884E6734a/112022</link>
    <fanart></fanart>
    <info>Canais | Portugal</info>
  </item>
  <item>
    <title>Disney Marvel</title>
    <thumbnail>http://beststorage4you.com:80/logoscanais/Portugal.png</thumbnail>
    <link>http://unividia.com:80/746147216xtvs/w884E6734a/112020</link>
    <fanart></fanart>
    <info>Canais | Portugal</info>
  </item>
  <item>
    <title>Disney Pixar</title>
    <thumbnail>http://beststorage4you.com:80/logoscanais/Portugal.png</thumbnail>
    <link>http://unividia.com:80/746147216xtvs/w884E6734a/112019</link>
    <fanart></fanart>
    <info>Canais | Portugal</info>
  </item>
  <item>
    <title>Disney Star Wars</title>
    <thumbnail>http://beststorage4you.com:80/logoscanais/Portugal.png</thumbnail>
    <link>http://unividia.com:80/746147216xtvs/w884E6734a/112018</link>
    <fanart></fanart>
    <info>Canais | Portugal</info>
  </item>
  <item>
    <title>DOG TV FHD</title>
    <thumbnail>http://beststorage4you.com:80/logoscanais/Portugal.png</thumbnail>
    <link>http://unividia.com:80/746147216xtvs/w884E6734a/112054</link>
    <fanart></fanart>
    <info>Canais | Portugal</info>
  </item>
  <item>
    <title>E! Entertainment SD</title>
    <thumbnail>http://beststorage4you.com:80/logoscanais/Portugal.png</thumbnail>
    <link>http://unividia.com:80/746147216xtvs/w884E6734a/112049</link>
    <fanart></fanart>
    <info>Canais | Portugal</info>
  </item>
  <item>
    <title>Eeuro News</title>
    <thumbnail>http://beststorage4you.com:80/logoscanais/Portugal.png</thumbnail>
    <link>http://unividia.com:80/746147216xtvs/w884E6734a/112110</link>
    <fanart></fanart>
    <info>Canais | Portugal</info>
  </item>
  <item>
    <title>Fashion TV HD</title>
    <thumbnail>http://beststorage4you.com:80/logoscanais/Portugal.png</thumbnail>
    <link>http://unividia.com:80/746147216xtvs/w884E6734a/112068</link>
    <fanart></fanart>
    <info>Canais | Portugal</info>
  </item>
  <item>
    <title>Fight Box HD</title>
    <thumbnail>http://beststorage4you.com:80/logoscanais/Portugal.png</thumbnail>
    <link>http://unividia.com:80/746147216xtvs/w884E6734a/112086</link>
    <fanart></fanart>
    <info>Canais | Portugal</info>
  </item>
  <item>
    <title>Fight Network</title>
    <thumbnail>http://beststorage4you.com:80/logoscanais/Portugal.png</thumbnail>
    <link>http://unividia.com:80/746147216xtvs/w884E6734a/112087</link>
    <fanart></fanart>
    <info>Canais | Portugal</info>
  </item>
  <item>
    <title>Food Network</title>
    <thumbnail>http://beststorage4you.com:80/logoscanais/Portugal.png</thumbnail>
    <link>http://unividia.com:80/746147216xtvs/w884E6734a/112048</link>
    <fanart></fanart>
    <info>Canais | Portugal</info>
  </item>
  <item>
    <title>FOX Comedy HD</title>
    <thumbnail>http://beststorage4you.com:80/logoscanais/Portugal.png</thumbnail>
    <link>http://unividia.com:80/746147216xtvs/w884E6734a/111989</link>
    <fanart></fanart>
    <info>Canais | Portugal</info>
  </item>
  <item>
    <title>FOX Crime HD</title>
    <thumbnail>http://beststorage4you.com:80/logoscanais/Portugal.png</thumbnail>
    <link>http://unividia.com:80/746147216xtvs/w884E6734a/111987</link>
    <fanart></fanart>
    <info>Canais | Portugal</info>
  </item>
  <item>
    <title>FOX FHD</title>
    <thumbnail>http://beststorage4you.com:80/logoscanais/Portugal.png</thumbnail>
    <link>http://unividia.com:80/746147216xtvs/w884E6734a/111986</link>
    <fanart></fanart>
    <info>Canais | Portugal</info>
  </item>
  <item>
    <title>FOX HD</title>
    <thumbnail>http://beststorage4you.com:80/logoscanais/Portugal.png</thumbnail>
    <link>http://unividia.com:80/746147216xtvs/w884E6734a/111985</link>
    <fanart></fanart>
    <info>Canais | Portugal</info>
  </item>
  <item>
    <title>FOX Life FHD</title>
    <thumbnail>http://beststorage4you.com:80/logoscanais/Portugal.png</thumbnail>
    <link>http://unividia.com:80/746147216xtvs/w884E6734a/111992</link>
    <fanart></fanart>
    <info>Canais | Portugal</info>
  </item>
  <item>
    <title>FOX Life HD</title>
    <thumbnail>http://beststorage4you.com:80/logoscanais/Portugal.png</thumbnail>
    <link>http://unividia.com:80/746147216xtvs/w884E6734a/111991</link>
    <fanart></fanart>
    <info>Canais | Portugal</info>
  </item>
  <item>
    <title>FOX Muvies HD</title>
    <thumbnail>http://beststorage4you.com:80/logoscanais/Portugal.png</thumbnail>
    <link>http://unividia.com:80/746147216xtvs/w884E6734a/111969</link>
    <fanart></fanart>
    <info>Canais | Portugal</info>
  </item>
  <item>
    <title>Fuel TV FHD</title>
    <thumbnail>http://beststorage4you.com:80/logoscanais/Portugal.png</thumbnail>
    <link>http://unividia.com:80/746147216xtvs/w884E6734a/112072</link>
    <fanart></fanart>
    <info>Canais | Portugal</info>
  </item>
  <item>
    <title>Fuel TV HD</title>
    <thumbnail>http://beststorage4you.com:80/logoscanais/Portugal.png</thumbnail>
    <link>http://unividia.com:80/746147216xtvs/w884E6734a/112071</link>
    <fanart></fanart>
    <info>Canais | Portugal</info>
  </item>
  <item>
    <title>GINX</title>
    <thumbnail>http://beststorage4you.com:80/logoscanais/Portugal.png</thumbnail>
    <link>http://unividia.com:80/746147216xtvs/w884E6734a/112081</link>
    <fanart></fanart>
    <info>Canais | Portugal</info>
  </item>
  <item>
    <title>HBO Portugal</title>
    <thumbnail>http://beststorage4you.com:80/logoscanais/Portugal.png</thumbnail>
    <link>http://unividia.com:80/746147216xtvs/w884E6734a/111976</link>
    <fanart></fanart>
    <info>Canais | Portugal</info>
  </item>
  <item>
    <title>Hollywood HD</title>
    <thumbnail>http://beststorage4you.com:80/logoscanais/Portugal.png</thumbnail>
    <link>http://unividia.com:80/746147216xtvs/w884E6734a/111967</link>
    <fanart></fanart>
    <info>Canais | Portugal</info>
  </item>
  <item>
    <title>ID Invesigation Discovery HD</title>
    <thumbnail>http://beststorage4you.com:80/logoscanais/Portugal.png</thumbnail>
    <link>http://unividia.com:80/746147216xtvs/w884E6734a/112064</link>
    <fanart></fanart>
    <info>Canais | Portugal</info>
  </item>
  <item>
    <title>Jim Jam SD</title>
    <thumbnail>http://beststorage4you.com:80/logoscanais/Portugal.png</thumbnail>
    <link>http://unividia.com:80/746147216xtvs/w884E6734a/112024</link>
    <fanart></fanart>
    <info>Canais | Portugal</info>
  </item>
  <item>
    <title>Kuriakos TV FHD</title>
    <thumbnail>http://beststorage4you.com:80/logoscanais/Portugal.png</thumbnail>
    <link>http://unividia.com:80/746147216xtvs/w884E6734a/112105</link>
    <fanart></fanart>
    <info>Canais | Portugal</info>
  </item>
  <item>
    <title>Lolly Kids</title>
    <thumbnail>http://beststorage4you.com:80/logoscanais/Portugal.png</thumbnail>
    <link>http://unividia.com:80/746147216xtvs/w884E6734a/112091</link>
    <fanart></fanart>
    <info>Canais | Portugal</info>
  </item>
  <item>
    <title>M6 Music HD</title>
    <thumbnail>http://beststorage4you.com:80/logoscanais/Portugal.png</thumbnail>
    <link>http://unividia.com:80/746147216xtvs/w884E6734a/112103</link>
    <fanart></fanart>
    <info>Canais | Portugal</info>
  </item>
  <item>
    <title>MCM POP SD</title>
    <thumbnail>http://beststorage4you.com:80/logoscanais/Portugal.png</thumbnail>
    <link>http://unividia.com:80/746147216xtvs/w884E6734a/112098</link>
    <fanart></fanart>
    <info>Canais | Portugal</info>
  </item>
  <item>
    <title>MCM TOP</title>
    <thumbnail>http://beststorage4you.com:80/logoscanais/Portugal.png</thumbnail>
    <link>http://unividia.com:80/746147216xtvs/w884E6734a/112097</link>
    <fanart></fanart>
    <info>Canais | Portugal</info>
  </item>
  <item>
    <title>Mezzo Live FHD</title>
    <thumbnail>http://beststorage4you.com:80/logoscanais/Portugal.png</thumbnail>
    <link>http://unividia.com:80/746147216xtvs/w884E6734a/112099</link>
    <fanart></fanart>
    <info>Canais | Portugal</info>
  </item>
  <item>
    <title>MotorVision TV SD</title>
    <thumbnail>http://beststorage4you.com:80/logoscanais/Portugal.png</thumbnail>
    <link>http://unividia.com:80/746147216xtvs/w884E6734a/112076</link>
    <fanart></fanart>
    <info>Canais | Portugal</info>
  </item>
  <item>
    <title>MTV Live HD</title>
    <thumbnail>http://beststorage4you.com:80/logoscanais/Portugal.png</thumbnail>
    <link>http://unividia.com:80/746147216xtvs/w884E6734a/112096</link>
    <fanart></fanart>
    <info>Canais | Portugal</info>
  </item>
  <item>
    <title>MTV Portugal HD</title>
    <thumbnail>http://beststorage4you.com:80/logoscanais/Portugal.png</thumbnail>
    <link>http://unividia.com:80/746147216xtvs/w884E6734a/112095</link>
    <fanart></fanart>
    <info>Canais | Portugal</info>
  </item>
  <item>
    <title>Más Chic HD</title>
    <thumbnail>http://beststorage4you.com:80/logoscanais/Portugal.png</thumbnail>
    <link>http://unividia.com:80/746147216xtvs/w884E6734a/112047</link>
    <fanart></fanart>
    <info>Canais | Portugal</info>
  </item>
  <item>
    <title>Nick + HD</title>
    <thumbnail>http://beststorage4you.com:80/logoscanais/Portugal.png</thumbnail>
    <link>http://unividia.com:80/746147216xtvs/w884E6734a/112021</link>
    <fanart></fanart>
    <info>Canais | Portugal</info>
  </item>
  <item>
    <title>Nickelodeon SD</title>
    <thumbnail>http://beststorage4you.com:80/logoscanais/Portugal.png</thumbnail>
    <link>http://unividia.com:80/746147216xtvs/w884E6734a/112025</link>
    <fanart></fanart>
    <info>Canais | Portugal</info>
  </item>
  <item>
    <title>NOS StudiosHD</title>
    <thumbnail>http://beststorage4you.com:80/logoscanais/Portugal.png</thumbnail>
    <link>http://unividia.com:80/746147216xtvs/w884E6734a/111965</link>
    <fanart></fanart>
    <info>Canais | Portugal</info>
  </item>
  <item>
    <title>Odisseia HD</title>
    <thumbnail>http://beststorage4you.com:80/logoscanais/Portugal.png</thumbnail>
    <link>http://unividia.com:80/746147216xtvs/w884E6734a/112065</link>
    <fanart></fanart>
    <info>Canais | Portugal</info>
  </item>
  <item>
    <title>Outdoor HD</title>
    <thumbnail>http://beststorage4you.com:80/logoscanais/Portugal.png</thumbnail>
    <link>http://unividia.com:80/746147216xtvs/w884E6734a/112077</link>
    <fanart></fanart>
    <info>Canais | Portugal</info>
  </item>
  <item>
    <title>Panda Biggs SD</title>
    <thumbnail>http://beststorage4you.com:80/logoscanais/Portugal.png</thumbnail>
    <link>http://unividia.com:80/746147216xtvs/w884E6734a/112029</link>
    <fanart></fanart>
    <info>Canais | Portugal</info>
  </item>
  <item>
    <title>PFC SD</title>
    <thumbnail>http://beststorage4you.com:80/logoscanais/Portugal.png</thumbnail>
    <link>http://unividia.com:80/746147216xtvs/w884E6734a/112070</link>
    <fanart></fanart>
    <info>Canais | Portugal</info>
  </item>
  <item>
    <title>Porto Canal HD</title>
    <thumbnail>http://beststorage4you.com:80/logoscanais/Portugal.png</thumbnail>
    <link>http://unividia.com:80/746147216xtvs/w884E6734a/112051</link>
    <fanart></fanart>
    <info>Canais | Portugal</info>
  </item>
  <item>
    <title>PT- 24 Kitchen HD</title>
    <thumbnail>http://beststorage4you.com:80/logoscanais/Portugal.png</thumbnail>
    <link>http://unividia.com:80/746147216xtvs/w884E6734a/112046</link>
    <fanart></fanart>
    <info>Canais | Portugal</info>
  </item>
  <item>
    <title>PT- AMC HD</title>
    <thumbnail>http://beststorage4you.com:80/logoscanais/Portugal.png</thumbnail>
    <link>http://unividia.com:80/746147216xtvs/w884E6734a/111973</link>
    <fanart></fanart>
    <info>Canais | Portugal</info>
  </item>
  <item>
    <title>PT- AXN HD</title>
    <thumbnail>http://beststorage4you.com:80/logoscanais/Portugal.png</thumbnail>
    <link>http://unividia.com:80/746147216xtvs/w884E6734a/111977</link>
    <fanart></fanart>
    <info>Canais | Portugal</info>
  </item>
  <item>
    <title>PT- AXN MOVIES  HD</title>
    <thumbnail>http://beststorage4you.com:80/logoscanais/Portugal.png</thumbnail>
    <link>http://unividia.com:80/746147216xtvs/w884E6734a/111981</link>
    <fanart></fanart>
    <info>Canais | Portugal</info>
  </item>
  <item>
    <title>PT- AXN WHITE HD</title>
    <thumbnail>http://beststorage4you.com:80/logoscanais/Portugal.png</thumbnail>
    <link>http://unividia.com:80/746147216xtvs/w884E6734a/111979</link>
    <fanart></fanart>
    <info>Canais | Portugal</info>
  </item>
  <item>
    <title>PT- Blaze HD</title>
    <thumbnail>http://beststorage4you.com:80/logoscanais/Portugal.png</thumbnail>
    <link>http://unividia.com:80/746147216xtvs/w884E6734a/112053</link>
    <fanart></fanart>
    <info>Canais | Portugal</info>
  </item>
  <item>
    <title>PT- Combate HD</title>
    <thumbnail>http://beststorage4you.com:80/logoscanais/Portugal.png</thumbnail>
    <link>http://unividia.com:80/746147216xtvs/w884E6734a/112083</link>
    <fanart></fanart>
    <info>Canais | Portugal</info>
  </item>
  <item>
    <title>PT- Marvel</title>
    <thumbnail>http://beststorage4you.com:80/logoscanais/Portugal.png</thumbnail>
    <link>http://unividia.com:80/746147216xtvs/w884E6734a/111935</link>
    <fanart></fanart>
    <info>Canais | Portugal</info>
  </item>
  <item>
    <title>PT- RTP 1 HD</title>
    <thumbnail>http://beststorage4you.com:80/logoscanais/Portugal.png</thumbnail>
    <link>http://unividia.com:80/746147216xtvs/w884E6734a/111937</link>
    <fanart></fanart>
    <info>Canais | Portugal</info>
  </item>
  <item>
    <title>PT- RTP 2 HD</title>
    <thumbnail>http://beststorage4you.com:80/logoscanais/Portugal.png</thumbnail>
    <link>http://unividia.com:80/746147216xtvs/w884E6734a/111939</link>
    <fanart></fanart>
    <info>Canais | Portugal</info>
  </item>
  <item>
    <title>PT- RTP 3 HD</title>
    <thumbnail>http://beststorage4you.com:80/logoscanais/Portugal.png</thumbnail>
    <link>http://unividia.com:80/746147216xtvs/w884E6734a/111949</link>
    <fanart></fanart>
    <info>Canais | Portugal</info>
  </item>
  <item>
    <title>PT- RTP Africa SD</title>
    <thumbnail>http://beststorage4you.com:80/logoscanais/Portugal.png</thumbnail>
    <link>http://unividia.com:80/746147216xtvs/w884E6734a/112057</link>
    <fanart></fanart>
    <info>Canais | Portugal</info>
  </item>
  <item>
    <title>PT- RTP Açores SD</title>
    <thumbnail>http://beststorage4you.com:80/logoscanais/Portugal.png</thumbnail>
    <link>http://unividia.com:80/746147216xtvs/w884E6734a/112056</link>
    <fanart></fanart>
    <info>Canais | Portugal</info>
  </item>
  <item>
    <title>PT- RTP MADEIRA</title>
    <thumbnail>http://beststorage4you.com:80/logoscanais/Portugal.png</thumbnail>
    <link>http://unividia.com:80/746147216xtvs/w884E6734a/112058</link>
    <fanart></fanart>
    <info>Canais | Portugal</info>
  </item>
  <item>
    <title>PT- RTP Memória SD</title>
    <thumbnail>http://beststorage4you.com:80/logoscanais/Portugal.png</thumbnail>
    <link>http://unividia.com:80/746147216xtvs/w884E6734a/112055</link>
    <fanart></fanart>
    <info>Canais | Portugal</info>
  </item>
  <item>
    <title>Red Bull TV  FHD</title>
    <thumbnail>http://beststorage4you.com:80/logoscanais/Portugal.png</thumbnail>
    <link>http://unividia.com:80/746147216xtvs/w884E6734a/112080</link>
    <fanart></fanart>
    <info>Canais | Portugal</info>
  </item>
  <item>
    <title>SIC Caras HD</title>
    <thumbnail>http://beststorage4you.com:80/logoscanais/Portugal.png</thumbnail>
    <link>http://unividia.com:80/746147216xtvs/w884E6734a/112039</link>
    <fanart></fanart>
    <info>Canais | Portugal</info>
  </item>
  <item>
    <title>SIC HD</title>
    <thumbnail>http://beststorage4you.com:80/logoscanais/Portugal.png</thumbnail>
    <link>http://unividia.com:80/746147216xtvs/w884E6734a/111941</link>
    <fanart></fanart>
    <info>Canais | Portugal</info>
  </item>
  <item>
    <title>SIC Kids HD</title>
    <thumbnail>http://beststorage4you.com:80/logoscanais/Portugal.png</thumbnail>
    <link>http://unividia.com:80/746147216xtvs/w884E6734a/112028</link>
    <fanart></fanart>
    <info>Canais | Portugal</info>
  </item>
  <item>
    <title>SIC Mulher HD</title>
    <thumbnail>http://beststorage4you.com:80/logoscanais/Portugal.png</thumbnail>
    <link>http://unividia.com:80/746147216xtvs/w884E6734a/112040</link>
    <fanart></fanart>
    <info>Canais | Portugal</info>
  </item>
  <item>
    <title>SIC Noticias HD</title>
    <thumbnail>http://beststorage4you.com:80/logoscanais/Portugal.png</thumbnail>
    <link>http://unividia.com:80/746147216xtvs/w884E6734a/111952</link>
    <fanart></fanart>
    <info>Canais | Portugal</info>
  </item>
  <item>
    <title>SIC Radical HD</title>
    <thumbnail>http://beststorage4you.com:80/logoscanais/Portugal.png</thumbnail>
    <link>http://unividia.com:80/746147216xtvs/w884E6734a/112041</link>
    <fanart></fanart>
    <info>Canais | Portugal</info>
  </item>
  <item>
    <title>Star + HD</title>
    <thumbnail>http://beststorage4you.com:80/logoscanais/Portugal.png</thumbnail>
    <link>http://unividia.com:80/746147216xtvs/w884E6734a/111975</link>
    <fanart></fanart>
    <info>Canais | Portugal</info>
  </item>
  <item>
    <title>SYFY HD</title>
    <thumbnail>http://beststorage4you.com:80/logoscanais/Portugal.png</thumbnail>
    <link>http://unividia.com:80/746147216xtvs/w884E6734a/111983</link>
    <fanart></fanart>
    <info>Canais | Portugal</info>
  </item>
  <item>
    <title>TCV Internacioanal</title>
    <thumbnail>http://beststorage4you.com:80/logoscanais/Portugal.png</thumbnail>
    <link>http://unividia.com:80/746147216xtvs/w884E6734a/112108</link>
    <fanart></fanart>
    <info>Canais | Portugal</info>
  </item>
  <item>
    <title>TLC SD</title>
    <thumbnail>http://beststorage4you.com:80/logoscanais/Portugal.png</thumbnail>
    <link>http://unividia.com:80/746147216xtvs/w884E6734a/112044</link>
    <fanart></fanart>
    <info>Canais | Portugal</info>
  </item>
  <item>
    <title>Toros TV FHD</title>
    <thumbnail>http://beststorage4you.com:80/logoscanais/Portugal.png</thumbnail>
    <link>http://unividia.com:80/746147216xtvs/w884E6734a/112074</link>
    <fanart></fanart>
    <info>Canais | Portugal</info>
  </item>
  <item>
    <title>Toros TV HD</title>
    <thumbnail>http://beststorage4you.com:80/logoscanais/Portugal.png</thumbnail>
    <link>http://unividia.com:80/746147216xtvs/w884E6734a/112073</link>
    <fanart></fanart>
    <info>Canais | Portugal</info>
  </item>
  <item>
    <title>TPA Internacional SD</title>
    <thumbnail>http://beststorage4you.com:80/logoscanais/Portugal.png</thumbnail>
    <link>http://unividia.com:80/746147216xtvs/w884E6734a/112106</link>
    <fanart></fanart>
    <info>Canais | Portugal</info>
  </item>
  <item>
    <title>Trace Urban</title>
    <thumbnail>http://beststorage4you.com:80/logoscanais/Portugal.png</thumbnail>
    <link>http://unividia.com:80/746147216xtvs/w884E6734a/112094</link>
    <fanart></fanart>
    <info>Canais | Portugal</info>
  </item>
  <item>
    <title>Travel Channel HD</title>
    <thumbnail>http://beststorage4you.com:80/logoscanais/Portugal.png</thumbnail>
    <link>http://unividia.com:80/746147216xtvs/w884E6734a/112050</link>
    <fanart></fanart>
    <info>Canais | Portugal</info>
  </item>
  <item>
    <title>TV Cine Action HD</title>
    <thumbnail>http://beststorage4you.com:80/logoscanais/Portugal.png</thumbnail>
    <link>http://unividia.com:80/746147216xtvs/w884E6734a/111963</link>
    <fanart></fanart>
    <info>Canais | Portugal</info>
  </item>
  <item>
    <title>TV Cine Edition HD</title>
    <thumbnail>http://beststorage4you.com:80/logoscanais/Portugal.png</thumbnail>
    <link>http://unividia.com:80/746147216xtvs/w884E6734a/111958</link>
    <fanart></fanart>
    <info>Canais | Portugal</info>
  </item>
  <item>
    <title>TV Cine Emotion HD</title>
    <thumbnail>http://beststorage4you.com:80/logoscanais/Portugal.png</thumbnail>
    <link>http://unividia.com:80/746147216xtvs/w884E6734a/111961</link>
    <fanart></fanart>
    <info>Canais | Portugal</info>
  </item>
  <item>
    <title>TV Cine Top HD</title>
    <thumbnail>http://beststorage4you.com:80/logoscanais/Portugal.png</thumbnail>
    <link>http://unividia.com:80/746147216xtvs/w884E6734a/111956</link>
    <fanart></fanart>
    <info>Canais | Portugal</info>
  </item>
  <item>
    <title>TV Record HD</title>
    <thumbnail>http://beststorage4you.com:80/logoscanais/Portugal.png</thumbnail>
    <link>http://unividia.com:80/746147216xtvs/w884E6734a/112038</link>
    <fanart></fanart>
    <info>Canais | Portugal</info>
  </item>
  <item>
    <title>TVC Cabo Verde</title>
    <thumbnail>http://beststorage4you.com:80/logoscanais/Portugal.png</thumbnail>
    <link>http://unividia.com:80/746147216xtvs/w884E6734a/112109</link>
    <fanart></fanart>
    <info>Canais | Portugal</info>
  </item>
  <item>
    <title>TVCine + HD</title>
    <thumbnail>http://beststorage4you.com:80/logoscanais/Portugal.png</thumbnail>
    <link>http://unividia.com:80/746147216xtvs/w884E6734a/111955</link>
    <fanart></fanart>
    <info>Canais | Portugal</info>
  </item>
  <item>
    <title>TVI FicçãoHD</title>
    <thumbnail>http://beststorage4you.com:80/logoscanais/Portugal.png</thumbnail>
    <link>http://unividia.com:80/746147216xtvs/w884E6734a/112033</link>
    <fanart></fanart>
    <info>Canais | Portugal</info>
  </item>
  <item>
    <title>TVI HD</title>
    <thumbnail>http://beststorage4you.com:80/logoscanais/Portugal.png</thumbnail>
    <link>http://unividia.com:80/746147216xtvs/w884E6734a/111943</link>
    <fanart></fanart>
    <info>Canais | Portugal</info>
  </item>
  <item>
    <title>TVI Reality</title>
    <thumbnail>http://beststorage4you.com:80/logoscanais/Portugal.png</thumbnail>
    <link>http://unividia.com:80/746147216xtvs/w884E6734a/112113</link>
    <fanart></fanart>
    <info>Canais | Portugal</info>
  </item>
  <item>
    <title>TVI Reality FHD</title>
    <thumbnail>http://beststorage4you.com:80/logoscanais/Portugal.png</thumbnail>
    <link>http://unividia.com:80/746147216xtvs/w884E6734a/112114</link>
    <fanart></fanart>
    <info>Canais | Portugal</info>
  </item>
  <item>
    <title>TVI Reality HD</title>
    <thumbnail>http://beststorage4you.com:80/logoscanais/Portugal.png</thumbnail>
    <link>http://unividia.com:80/746147216xtvs/w884E6734a/112035</link>
    <fanart></fanart>
    <info>Canais | Portugal</info>
  </item>
  <item>
    <title>TVI Reality Low</title>
    <thumbnail>http://beststorage4you.com:80/logoscanais/Portugal.png</thumbnail>
    <link>http://unividia.com:80/746147216xtvs/w884E6734a/112112</link>
    <fanart></fanart>
    <info>Canais | Portugal</info>
  </item>
  <item>
    <title>TVI Reality Mosaico</title>
    <thumbnail>http://beststorage4you.com:80/logoscanais/Portugal.png</thumbnail>
    <link>http://unividia.com:80/746147216xtvs/w884E6734a/112111</link>
    <fanart></fanart>
    <info>Canais | Portugal</info>
  </item>
  <item>
    <title>VH1 SD</title>
    <thumbnail>http://beststorage4you.com:80/logoscanais/Portugal.png</thumbnail>
    <link>http://unividia.com:80/746147216xtvs/w884E6734a/112093</link>
    <fanart></fanart>
    <info>Canais | Portugal</info>
  </item>
  <item>
    <title>WWE HD</title>
    <thumbnail>http://beststorage4you.com:80/logoscanais/Portugal.png</thumbnail>
    <link>http://unividia.com:80/746147216xtvs/w884E6734a/112085</link>
    <fanart></fanart>
    <info>Canais | Portugal</info>
  </item>
  <item>
    <title>Zap Viva FHD</title>
    <thumbnail>http://beststorage4you.com:80/logoscanais/Portugal.png</thumbnail>
    <link>http://unividia.com:80/746147216xtvs/w884E6734a/112104</link>
    <fanart></fanart>
    <info>Canais | Portugal</info>
  </item>
  <item>
    <title>TV Globo HD</title>
    <thumbnail>http://beststorage4you.com:80/logoscanais/Portugal.png</thumbnail>
    <link>http://unividia.com:80/746147216xtvs/w884E6734a/377249</link>
    <fanart></fanart>
    <info>Canais | Portugal</info>
  </item>

